stock_analyzer/__init__.py
stock_analyzer/cli.py
stock_analyzer/config.py
stock_analyzer/core.py
stock_analyzer/tests/__init__.py
stock_analyzer/tests/test_cli.py
stock_analyzer/tests/test_core.py
stock_analyzer-0.0.1.dist-info/LICENSE
stock_analyzer-0.0.1.dist-info/METADATA
stock_analyzer-0.0.1.dist-info/WHEEL
stock_analyzer-0.0.1.dist-info/entry_points.txt
stock_analyzer-0.0.1.dist-info/top_level.txt
stock_analyzer-0.0.1.dist-info/RECORD
