Metadata-Version: 2.1
Name: stock-analyzer
Version: 0.0.1
Summary: A package for analyzing stock patterns
Home-page: https://github.com/daballachris/stock_analyzer
Author: Christopher Duane Smith
Author-email: daballachris@protonmail.com
License: MIT
Platform: UNKNOWN
